django_debugger/__init__.py
django_debugger/management/__init__.py
django_debugger/management/commands/__init__.py
django_debugger/management/commands/runserver.py
django_debugger-0.6.dist-info/LICENSE
django_debugger-0.6.dist-info/METADATA
django_debugger-0.6.dist-info/WHEEL
django_debugger-0.6.dist-info/top_level.txt
django_debugger-0.6.dist-info/RECORD
