Metadata-Version: 2.1
Name: django-debugger
Version: 0.6
Summary: A simple plugin to attach a debugger in Django during runserver
Home-page: https://github.com/sajalshres/django-debugger
Author: Sajal Shrestha
Author-email: sajal.shres@gmail.com
License: MIT
Keywords: DJANGO,DEBUGGER,DEBUGPY,PYTHON
Platform: UNKNOWN
Classifier: Development Status :: 3 - Alpha
Classifier: Intended Audience :: Developers
Classifier: Topic :: Software Development :: Build Tools
Classifier: License :: OSI Approved :: MIT License
Classifier: Programming Language :: Python :: 3
Classifier: Programming Language :: Python :: 3.4
Classifier: Programming Language :: Python :: 3.5
Classifier: Programming Language :: Python :: 3.6
Classifier: Programming Language :: Python :: 3.7
Classifier: Programming Language :: Python :: 3.8
Classifier: Operating System :: OS Independent
License-File: LICENSE
Requires-Dist: debugpy (==1.3.0)
